projects_carousel/__init__.py
projects_carousel/frontend/index.html
projects_carousel/frontend/main.js
projects_carousel/frontend/streamlit-component-lib.js
projects_carousel/frontend/style.css
projects_carousel/frontend/css/swiper-bundle.min.css
projects_carousel/frontend/images/profile1.jpg
projects_carousel/frontend/images/profile2.jpg
projects_carousel/frontend/images/profile3.jpg
projects_carousel/frontend/images/profile4.jpg
projects_carousel/frontend/images/profile5.jpg
projects_carousel/frontend/images/profile6.jpg
projects_carousel/frontend/js/script.js
projects_carousel/frontend/js/swiper-bundle.min.js
projects_carousel-0.1.0.dist-info/LICENSE
projects_carousel-0.1.0.dist-info/METADATA
projects_carousel-0.1.0.dist-info/WHEEL
projects_carousel-0.1.0.dist-info/top_level.txt
projects_carousel-0.1.0.dist-info/RECORD
